pykun/__init__.py
pykun/strControl.py
pykun/file/__init__.py
pykun/file/configure.py
pykun/file/copier.py
pykun/file/log.py
pykun-0.1.3.dist-info/LICENSE
pykun-0.1.3.dist-info/METADATA
pykun-0.1.3.dist-info/WHEEL
pykun-0.1.3.dist-info/top_level.txt
pykun-0.1.3.dist-info/RECORD
