Metadata-Version: 2.1
Name: pykun
Version: 0.1.3
Summary: Develop a Callection of useful packages
Home-page: https://github.com/kunrunic/pykun
Author: Jho Sung Jun
Author-email: kunrunic7272@gmail.com
License: MIT
Platform: UNKNOWN
